dsslab/wdc_client/__init__.py
dsslab/wdc_client/client.py
dsslab_wdc_client-0.17.0.dist-info/METADATA
dsslab_wdc_client-0.17.0.dist-info/WHEEL
dsslab_wdc_client-0.17.0.dist-info/RECORD
