Metadata-Version: 2.4
Name: dsslab-wdc-client
Version: 0.17.0
Summary: A small client for the WDC-Rest-API.
Author: Tino Schöllhorn
Author-email: t.schoellhorn@uni-mannheim.de
Requires-Python: >=3.10,<4
Classifier: Programming Language :: Python :: 3
Classifier: Programming Language :: Python :: 3.10
Classifier: Programming Language :: Python :: 3.11
Classifier: Programming Language :: Python :: 3.12
Classifier: Programming Language :: Python :: 3.13
Classifier: Programming Language :: Python :: 3.14
Provides-Extra: docs
Requires-Dist: Sphinx (==7.4.7) ; extra == "docs"
Requires-Dist: json-stream (>=2.4.1)
Requires-Dist: networkx (>=3.4)
Requires-Dist: pandas[excel, plot] (>=2.2,<3.0)
Requires-Dist: python-dotenv (>=1.1.0)
Requires-Dist: requests (>=2.3)
Requires-Dist: sphinx-rtd-theme (==3.0.2) ; extra == "docs"
Requires-Dist: sphinxcontrib-napoleon (==0.7) ; extra == "docs"
Project-URL: Documentation, https://dss-wdc.wiso.uni-hamburg.de/dsslab_wdc_client_docs/html/index.html
Project-URL: Homepage, https://dss-wdc.wiso.uni-hamburg.de/
